poetry_source_env/__init__.py
poetry_source_env/plugin.py
poetry_source_env-2.0.1.dist-info/LICENSE.md
poetry_source_env-2.0.1.dist-info/METADATA
poetry_source_env-2.0.1.dist-info/WHEEL
poetry_source_env-2.0.1.dist-info/entry_points.txt
poetry_source_env-2.0.1.dist-info/RECORD
