Metadata-Version: 2.1
Name: poetry-source-env
Version: 2.0.1
Summary: Load Poetry package sources from environment variables
Home-page: https://github.com/celsiusnarhwal/poetry-source-env
License: MIT
Author: celsius narhwal
Author-email: hello@celsiusnarhwal.dev
Requires-Python: >=3.8,<4.0
Classifier: License :: OSI Approved :: MIT License
Classifier: Programming Language :: Python :: 3
Classifier: Programming Language :: Python :: 3.8
Classifier: Programming Language :: Python :: 3.9
Classifier: Programming Language :: Python :: 3.10
Classifier: Programming Language :: Python :: 3.11
Requires-Dist: dict-deep (>=4.1.2,<5.0.0)
Requires-Dist: poetry (>=1.5.0,<2.0.0)
Requires-Dist: pydantic (>=1.10.7,<2.0.0)
Project-URL: Repository, https://github.com/celsiusnarhwal/poetry-source-env
